{
  "project_info": {
    "project_number": "275579000535",
    "firebase_url": "https://restaurant-finder-a8b57.firebaseio.com",
    "project_id": "restaurant-finder-a8b57",
    "storage_bucket": "restaurant-finder-a8b57.appspot.com"
  },
  "client": [
    {
      "client_info": {
        "mobilesdk_app_id": "1:275579000535:android:dd5d3ca0cc792b28d74292",
        "android_client_info": {
          "package_name": "com.example.restaurantfinder"
        }
      },
      "oauth_client": [
        {
          "client_id": "275579000535-52pkeoi3p91a0un28as9es72fq0mj5s1.apps.googleusercontent.com",
          "client_type": 1,
          "android_info": {
            "package_name": "com.example.restaurantfinder",
            "certificate_hash": "2d2d055029a03025888da446365c548ba16322eb"
          }
        },
        {
          "client_id": "275579000535-nkah8hsrffscshldogurnkts86mi4rjf.apps.googleusercontent.com",
          "client_type": 3
        }
      ],
      "api_key": [
        {
          "current_key": "AIzaSyBFPmIPLka3VEFMGRQ9647_JenqBM3K7bY"
        }
      ],
      "services": {
        "appinvite_service": {
          "other_platform_oauth_client": [
            {
              "client_id": "275579000535-nkah8hsrffscshldogurnkts86mi4rjf.apps.googleusercontent.com",
              "client_type": 3
            }
          ]
        }
      }
    }
  ],
  "configuration_version": "1"
}